{
  "timestamp": "2025-12-01T18:06:25.715Z",
  "results": [
    {
      "name": "Homepage loads",
      "passed": true,
      "timestamp": "2025-12-01T18:06:26.396Z",
      "details": ""
    },
    {
      "name": "Page title correct",
      "passed": true,
      "timestamp": "2025-12-01T18:06:26.440Z",
      "details": "Nexus AI // Professional"
    },
    {
      "name": "Login form renders",
      "passed": true,
      "timestamp": "2025-12-01T18:06:26.492Z",
      "details": ""
    },
    {
      "name": "Health endpoint responds",
      "passed": true,
      "timestamp": "2025-12-01T18:06:26.539Z",
      "details": "Status: 503"
    },
    {
      "name": "CSS/JS loaded",
      "passed": true,
      "timestamp": "2025-12-01T18:06:26.558Z",
      "details": "CSS: loaded, JS: loaded"
    },
    {
      "name": "Security headers present",
      "passed": "0",
      "timestamp": "2025-12-01T18:06:26.573Z",
      "details": ""
    },
    {
      "name": "No fatal console errors",
      "passed": true,
      "timestamp": "2025-12-01T18:06:28.589Z",
      "details": "Found: 0 errors"
    },
    {
      "name": "Mobile viewport works",
      "passed": true,
      "timestamp": "2025-12-01T18:06:28.789Z",
      "details": ""
    },
    {
      "name": "Form validation attributes",
      "passed": true,
      "timestamp": "2025-12-01T18:06:28.838Z",
      "details": ""
    },
    {
      "name": "404 page handling",
      "passed": true,
      "timestamp": "2025-12-01T18:06:28.854Z",
      "details": "Status: 404"
    },
    {
      "name": "Backend connectivity",
      "passed": true,
      "timestamp": "2025-12-01T18:06:28.869Z",
      "details": ""
    },
    {
      "name": "API endpoints accessible",
      "passed": true,
      "timestamp": "2025-12-01T18:06:28.884Z",
      "details": "Status: 503"
    }
  ],
  "errors": [],
  "warnings": [
    {
      "type": "console_error",
      "message": "Failed to load resource: the server responded with a status of 503 (Service Unavailable)"
    },
    {
      "type": "console_error",
      "message": "Failed to load resource: the server responded with a status of 404 (Not Found)"
    }
  ],
  "screenshots": [
    "01-homepage.png",
    "02-login-page.png"
  ]
}